docs/source/conf.py
protdata/__init__.py
protdata/io/__init__.py
protdata/io/diann_loader.py
protdata/io/fragpipe_loader.py
protdata/io/maxquant_loader.py
protdata/io/mztab_loader.py
protdata/io/utils.py
protdata-0.1.4.dist-info/licenses/LICENSE
tests/test_loaders.py
tests/test_maxquant_loader.py
protdata-0.1.4.dist-info/METADATA
protdata-0.1.4.dist-info/WHEEL
protdata-0.1.4.dist-info/top_level.txt
protdata-0.1.4.dist-info/RECORD
