Metadata-Version: 2.4
Name: protdata
Version: 0.1.4
Summary: Proteomics data loaders for AnnData format.
Author: Max Frank
License-Expression: MIT
Classifier: Programming Language :: Python :: 3
Classifier: Operating System :: OS Independent
Classifier: Development Status :: 3 - Alpha
Classifier: Intended Audience :: Science/Research
Classifier: Topic :: Scientific/Engineering :: Bio-Informatics
Requires-Python: <4.0,>=3.9
License-File: LICENSE
Requires-Dist: anndata
Requires-Dist: pandas
Requires-Dist: numpy
Requires-Dist: pyteomics
Provides-Extra: dev
Requires-Dist: pytest>=7.0.0; extra == "dev"
Requires-Dist: black~=25.1; extra == "dev"
Requires-Dist: flake8~=7.0; extra == "dev"
Requires-Dist: isort~=5.0; extra == "dev"
Requires-Dist: pre-commit~=3.0; extra == "dev"
Requires-Dist: pylint~=3.0; extra == "dev"
Requires-Dist: pytest~=8.0; extra == "dev"
Provides-Extra: docs
Requires-Dist: sphinx>=8.2.1; extra == "docs"
Requires-Dist: sphinx-book-theme>=1.1.0; extra == "docs"
Requires-Dist: sphinx-autodoc-typehints>=2.2.0; extra == "docs"
Requires-Dist: sphinx-issues>=5.0.1; extra == "docs"
Requires-Dist: sphinx-copybutton; extra == "docs"
Requires-Dist: sphinx-toolbox>=3.8.0; extra == "docs"
Requires-Dist: sphinxext.opengraph; extra == "docs"
Requires-Dist: sphinx_design; extra == "docs"
Requires-Dist: myst-nb; extra == "docs"
Requires-Dist: scanpydoc[theme,typehints]>=0.15.3; extra == "docs"
Requires-Dist: awkward>=2.3; extra == "docs"
Requires-Dist: IPython; extra == "docs"
Requires-Dist: myst_parser; extra == "docs"
Dynamic: license-file
